download_accelerator/__init__.py
download_accelerator/__main__.py
download_accelerator/cli.py
download_accelerator/constants.py
download_accelerator/file_tools.py
download_accelerator/network_tools.py
download_accelerator-1.0.1.dist-info/AUTHORS.rst
download_accelerator-1.0.1.dist-info/LICENSE
download_accelerator-1.0.1.dist-info/METADATA
download_accelerator-1.0.1.dist-info/WHEEL
download_accelerator-1.0.1.dist-info/entry_points.txt
download_accelerator-1.0.1.dist-info/top_level.txt
download_accelerator-1.0.1.dist-info/RECORD
