Metadata-Version: 2.1
Name: download-accelerator
Version: 1.0.1
Summary: A python accelerator based on python
Home-page: https://github.com/AriaBagheri/python-download-accelerator
Author: Aria Bagheri
Author-email: ariab9342@gmail.com
License: MIT
Project-URL: Documentation, https://python-download-accelerator.readthedocs.io/
Project-URL: Changelog, https://python-download-accelerator.readthedocs.io/en/latest/changelog.html
Project-URL: Issue Tracker, https://github.com/AriaBagheri/python-download-accelerator/issues
Platform: UNKNOWN
Classifier: Development Status :: 5 - Production/Stable
Classifier: Intended Audience :: Developers
Classifier: License :: OSI Approved :: MIT License
Classifier: Operating System :: Unix
Classifier: Operating System :: POSIX
Classifier: Operating System :: Microsoft :: Windows
Classifier: Programming Language :: Python :: 3
Classifier: Programming Language :: Python :: 3.7
Classifier: Programming Language :: Python :: 3.8
Classifier: Topic :: Utilities
Requires-Python: >3.5.0
Requires-Dist: aiohttp
Requires-Dist: argh
Requires-Dist: asyncio
Requires-Dist: click
Requires-Dist: funcy
Requires-Dist: tqdm
